[
    {
        "posx": 378.2209634460458,
        "posy": 523.6558253895269,
        "radio": 20,
        "direccion": 181,
        "color": "#34735d",
        "energia": 91.1000000000005,
        "descanso": 91.1000000000005,
        "rol": "IMPOSTOR",
        "inventario": [
            {
                "posx": 103,
                "posy": 464,
                "color": "#b469be"
            },
            {
                "posx": 422,
                "posy": 320,
                "color": "#d22639"
            }
        ],
        "logros": {
            "logros": {
                "Primer Logro": "Has completado tu primera mision."
            }
        }
    },
    {
        "posx": 638.611231623157,
        "posy": 67.7316820435621,
        "radio": 20,
        "direccion": 36,
        "color": "#8047f3",
        "energia": 91.1000000000005,
        "descanso": 91.1000000000005,
        "rol": "IMPOSTOR",
        "inventario": [
            {
                "posx": 456,
                "posy": 556,
                "color": "#6b85b3"
            },
            {
                "posx": 296,
                "posy": 499,
                "color": "#0b7f6c"
            }
        ],
        "logros": {
            "logros": {
                "Primer Logro": "Has completado tu primera mision."
            }
        }
    },
    {
        "posx": 192.076709804827,
        "posy": 234.3222515182203,
        "radio": 20,
        "direccion": 141,
        "color": "#d47ace",
        "energia": 91.1000000000005,
        "descanso": 91.1000000000005,
        "rol": "DETECTIVE",
        "inventario": [
            {
                "posx": 462,
                "posy": 355,
                "color": "#e8f6d1"
            },
            {
                "posx": 278,
                "posy": 64,
                "color": "#897a96"
            }
        ],
        "logros": {
            "logros": {
                "Primer Logro": "Has completado tu primera mision."
            }
        }
    },
    {
        "posx": 377.6515802075821,
        "posy": 689.8674854113929,
        "radio": 20,
        "direccion": 220,
        "color": "#ff7f19",
        "energia": 91.1000000000005,
        "descanso": 91.1000000000005,
        "rol": "DETECTIVE",
        "inventario": [
            {
                "posx": 555,
                "posy": 382,
                "color": "#8ca165"
            },
            {
                "posx": 556,
                "posy": 168,
                "color": "#8aa0b7"
            }
        ],
        "logros": {
            "logros": {
                "Primer Logro": "Has completado tu primera mision."
            }
        }
    },
    {
        "posx": 658.0073564730654,
        "posy": 605.8503568482747,
        "radio": 20,
        "direccion": 318,
        "color": "#3ae3ce",
        "energia": 91.1000000000005,
        "descanso": 91.1000000000005,
        "rol": "IMPOSTOR",
        "inventario": [
            {
                "posx": 655,
                "posy": 196,
                "color": "#241640"
            },
            {
                "posx": 610,
                "posy": 591,
                "color": "#dc7320"
            }
        ],
        "logros": {
            "logros": {
                "Primer Logro": "Has completado tu primera mision."
            }
        }
    }
]